text2qti/__init__.py
text2qti/cmdline.py
text2qti/config.py
text2qti/err.py
text2qti/export.py
text2qti/fmtversion.py
text2qti/markdown.py
text2qti/pymd_pandoc_attr.py
text2qti/qti.py
text2qti/quiz.py
text2qti/version.py
text2qti/xml_assessment.py
text2qti/xml_assessment_meta.py
text2qti/xml_imsmanifest.py
text2qti/gui/__init__.py
text2qti/gui/tk.py
text2qti-0.7.1.dist-info/CHANGELOG.md
text2qti-0.7.1.dist-info/LICENSE.txt
text2qti-0.7.1.dist-info/METADATA
text2qti-0.7.1.dist-info/WHEEL
text2qti-0.7.1.dist-info/entry_points.txt
text2qti-0.7.1.dist-info/top_level.txt
text2qti-0.7.1.dist-info/RECORD
