Metadata-Version: 2.1
Name: text2qti
Version: 0.7.1
Summary: Create quizzes in QTI format from Markdown-based plain text
Author-email: "Geoffrey M. Poore" <gpoore@gmail.com>
License: BSD 3-Clause License
Project-URL: repository, http://github.com/gpoore/text2qti
Project-URL: changelog, http://github.com/gpoore/text2qti/blob/master/CHANGELOG.md
Keywords: QTI,IMS Question & Test Interoperability,quiz,test,exam,assessment,markdown,LaTeX,plain text
Classifier: Development Status :: 4 - Beta
Classifier: Environment :: Console
Classifier: Intended Audience :: Education
Classifier: License :: OSI Approved :: BSD License
Classifier: Operating System :: OS Independent
Classifier: Programming Language :: Python
Classifier: Topic :: Education :: Testing
Requires-Python: >=3.8
License-File: LICENSE.txt
License-File: CHANGELOG.md
Requires-Dist: bespon >=0.7.0
Requires-Dist: markdown >=3.4.4
